[
  {
    "title": {
      "en": "Shaman",
      "ru": ""
    },
    "description": {
      "en": "Shamans are intermediaries between the seen and the unseen, blending ancient traditions with personal rituals passed down through spirit or blood. They carry the weight of ancestral knowledge in bark, bone, and breath, calling on powers both revered and feared. Some work in service of their community, others wander alone, led by whispers only they can hear. A shaman's strength lies not in command, but in connection to the spirits, to the land, and to the threads between all things. Few understand the cost of channeling unseen forces, and fewer still survive it unchanged.",
      "ru": ""
    },
    "public": true,
    "domains": ["sage", "dread"],
    "evasion": 10,
    "health_max": 6,
    "features": [
      {
        "title": {
          "en": "Curse",
          "ru": ""
        },
        "description": {
          "en": "**Spend 3 Hope** to force an adversary within Close range to mark a Stress.",
          "ru": ""
        },
        "kind": "static",
        "price": { "hope": 3 }
      },
      {
        "title": {
          "en": "Spirit Tether",
          "ru": "Духовная связь"
        },
        "description": {
          "en": "You can Tether a target within Close range, linking them to you until you fall unconscious or the scene ends. While Tethered, whenever you mark any number of Hit Points or Stress, you can **spend a Hope** to force them to mark one of the same.",
          "ru": ""
        },
        "kind": "static",
        "limit": 1,
        "limit_refresh": "long_rest"
      }
    ]
  }
]
